equilibrator_api/__init__.py
equilibrator_api/compatibility.py
equilibrator_api/component_contribution.py
equilibrator_api/phased_compound.py
equilibrator_api/phased_reaction.py
equilibrator_api/reaction_parser.py
equilibrator_api/data/__init__.py
equilibrator_api/data/cofactors.csv
equilibrator_api/model/__init__.py
equilibrator_api/model/bounds.py
equilibrator_api/model/model.py
equilibrator_api-0.6.0.dist-info/LICENSE
equilibrator_api-0.6.0.dist-info/METADATA
equilibrator_api-0.6.0.dist-info/WHEEL
equilibrator_api-0.6.0.dist-info/top_level.txt
equilibrator_api-0.6.0.dist-info/zip-safe
equilibrator_api-0.6.0.dist-info/RECORD
